gradio_spreadsheetcomponent/__init__.py
gradio_spreadsheetcomponent/__init__.pyi
gradio_spreadsheetcomponent/spreadsheetcomponent.py
gradio_spreadsheetcomponent/spreadsheetcomponent.pyi
gradio_spreadsheetcomponent/templates/component/index.js
gradio_spreadsheetcomponent/templates/example/index.js
gradio_spreadsheetcomponent/templates/example/style.css
gradio_spreadsheetcomponent-0.0.3.dist-info/METADATA
gradio_spreadsheetcomponent-0.0.3.dist-info/WHEEL
gradio_spreadsheetcomponent-0.0.3.dist-info/RECORD
