Metadata-Version: 2.4
Name: gradio_spreadsheetcomponent
Version: 0.0.3
Summary: This component is used to answer questions about spreadsheets.
Author-email: Mustafizur Rahman <mustafizz996@gmail.com>
License-Expression: Apache-2.0
Keywords: gradio-custom-component,gradio-spreadsheet-custom-component
Classifier: Development Status :: 3 - Alpha
Classifier: Operating System :: OS Independent
Classifier: Programming Language :: Python :: 3
Classifier: Programming Language :: Python :: 3 :: Only
Classifier: Programming Language :: Python :: 3.8
Classifier: Programming Language :: Python :: 3.9
Classifier: Programming Language :: Python :: 3.10
Classifier: Programming Language :: Python :: 3.11
Classifier: Topic :: Scientific/Engineering
Classifier: Topic :: Scientific/Engineering :: Artificial Intelligence
Classifier: Topic :: Scientific/Engineering :: Visualization
Requires-Python: >=3.10
Requires-Dist: gradio<6.0,>=4.0
Requires-Dist: huggingface-hub
Requires-Dist: openpyxl
Requires-Dist: pandas
